LICENSE
README.md
setup.py
Wdata/__init__.py
Wdata/data_py.py
Wdata/main.py
Wdata/mathfunc.py
Wdata/version.py
Wdata/all_error/__init__.py
Wdata/all_error/error_main.py
Wdata/plot_pic/Line_chart.py
Wdata/plot_pic/__init__.py
Wdata/read/__init__.py
Wdata/read/read_main.py
Wdatabase.egg-info/PKG-INFO
Wdatabase.egg-info/SOURCES.txt
Wdatabase.egg-info/dependency_links.txt
Wdatabase.egg-info/requires.txt
Wdatabase.egg-info/top_level.txt