Metadata-Version: 2.1
Name: Wdatabase
Version: 2.3.0
Summary: A database with multiple data sets that support drawing, These data sets are: World population data set, World Carbon dioxide Concentration data set, World Number of Cities data set, China number of population data set, China number of space vehicles data set......
Home-page: https://github.com/Wdataorg/Wdata
Author: Wdataorg
Author-email: rainwang_20220102@163.com
Maintainer: Wdataorg
Maintainer-email: rainwang_20220102@163.com
License:                                  Apache License
Project-URL: Documentation, https://github.com/Wdataorg/Wdata#readme
Project-URL: Source, https://github.com/Wdataorg/Wdata
Project-URL: Tracker, https://github.com/Wdataorg/Wdata/issues
Project-URL: Funding, https://wdataorg.github.io/Sponsor/
Platform: UNKNOWN
Classifier: Environment :: Console
Classifier: Natural Language :: Chinese (Simplified)
Classifier: Natural Language :: English
Classifier: Operating System :: Microsoft :: Windows
Classifier: Operating System :: Microsoft :: Windows :: Windows 10
Classifier: Development Status :: 5 - Production/Stable
Classifier: Topic :: Database :: Database Engines/Servers
Classifier: Environment :: Console
Classifier: Programming Language :: Python
Classifier: Programming Language :: Python :: 3.6
Classifier: Programming Language :: Python :: 3.7
Classifier: Programming Language :: Python :: 3.8
Classifier: Programming Language :: Python :: 3.9
Classifier: Programming Language :: Python :: 3.10
Classifier: Programming Language :: Python :: 3.11
Classifier: Programming Language :: Python :: Implementation
Classifier: Programming Language :: Python :: Implementation :: CPython
Classifier: Programming Language :: Python :: Implementation :: PyPy
Classifier: Operating System :: OS Independent
Requires-Python: >=3.8
License-File: LICENSE
